ehispassword/__init__.py
ehispassword/passwordexplainer.py
ehispassword/passwordgenerator.py
ehispassword-1.0.dist-info/LICENSE
ehispassword-1.0.dist-info/METADATA
ehispassword-1.0.dist-info/WHEEL
ehispassword-1.0.dist-info/top_level.txt
ehispassword-1.0.dist-info/RECORD
