Metadata-Version: 2.1
Name: ehispassword
Version: 1.0
License-File: LICENSE
